jentic/apitools/openapi/validator/backends/speclynx/__init__.py
jentic/apitools/openapi/validator/backends/speclynx/py.typed
jentic/apitools/openapi/validator/backends/speclynx/resources/jentic-openapi-validator-speclynx-0.1.0.tgz
jentic_openapi_validator_speclynx-1.0.0a34.dist-info/licenses/LICENSE
jentic_openapi_validator_speclynx-1.0.0a34.dist-info/licenses/NOTICE
jentic_openapi_validator_speclynx-1.0.0a34.dist-info/WHEEL
jentic_openapi_validator_speclynx-1.0.0a34.dist-info/entry_points.txt
jentic_openapi_validator_speclynx-1.0.0a34.dist-info/METADATA
jentic_openapi_validator_speclynx-1.0.0a34.dist-info/RECORD
